heartmap/__init__.py
heartmap/api/__init__.py
heartmap/config/__init__.py
heartmap/data/__init__.py
heartmap/data/lr_database.py
heartmap/models/__init__.py
heartmap/pipelines/__init__.py
heartmap/utils/__init__.py
heartmap-2.0.2.dist-info/licenses/LICENSE
heartmap-2.0.2.dist-info/licenses/NOTICE
heartmap-2.0.2.dist-info/METADATA
heartmap-2.0.2.dist-info/WHEEL
heartmap-2.0.2.dist-info/entry_points.txt
heartmap-2.0.2.dist-info/top_level.txt
heartmap-2.0.2.dist-info/RECORD
