Metadata-Version: 2.4
Name: heartmap
Version: 2.0.2
Summary: Heart Multi-chamber Analysis Platform for single-cell RNA-seq
Home-page: https://github.com/Tumo505/HeartMap
Author: Tumo Kgabeng, Lulu Wang, Harry Ngwangwa, Thanyani Pandelani
Author-email: 28346416@mylife.unisa.ac.za
Project-URL: Documentation, https://github.com/Tumo505/HeartMap/wiki
Project-URL: Source, https://github.com/Tumo505/HeartMap
Project-URL: Tracker, https://github.com/Tumo505/HeartMap/issues
Keywords: single-cell,RNA-seq,heart,cell-communication,bioinformatics,spatial-transcriptomics
Classifier: Development Status :: 4 - Beta
Classifier: Intended Audience :: Science/Research
Classifier: License :: OSI Approved :: Apache Software License
Classifier: Operating System :: OS Independent
Classifier: Programming Language :: Python :: 3
Classifier: Programming Language :: Python :: 3.8
Classifier: Programming Language :: Python :: 3.9
Classifier: Programming Language :: Python :: 3.10
Classifier: Programming Language :: Python :: 3.11
Classifier: Topic :: Scientific/Engineering :: Bio-Informatics
Requires-Python: >=3.8
License-File: LICENSE
License-File: NOTICE
Requires-Dist: scanpy>=1.9.0
Requires-Dist: pandas>=1.5.0
Requires-Dist: numpy>=1.21.0
Requires-Dist: scipy>=1.9.0
Requires-Dist: scikit-learn>=1.1.0
Requires-Dist: matplotlib>=3.5.0
Requires-Dist: seaborn>=0.11.0
Requires-Dist: anndata>=0.8.0
Requires-Dist: plotly>=5.0.0
Requires-Dist: networkx>=2.8.0
Requires-Dist: python-igraph>=0.10.0
Requires-Dist: leidenalg>=0.8.0
Requires-Dist: tqdm
Requires-Dist: statsmodels
Requires-Dist: pyyaml>=6.0
Provides-Extra: communication
Requires-Dist: liana>=0.1.0; extra == "communication"
Requires-Dist: cellphonedb>=3.0.0; extra == "communication"
Requires-Dist: omnipath>=1.0.0; extra == "communication"
Provides-Extra: api
Requires-Dist: fastapi>=0.100.0; extra == "api"
Requires-Dist: uvicorn>=0.23.0; extra == "api"
Requires-Dist: pydantic>=2.0.0; extra == "api"
Provides-Extra: dev
Requires-Dist: pytest>=7.0.0; extra == "dev"
Requires-Dist: pytest-cov>=4.0.0; extra == "dev"
Requires-Dist: black>=23.0.0; extra == "dev"
Requires-Dist: flake8>=6.0.0; extra == "dev"
Requires-Dist: mypy>=1.0.0; extra == "dev"
Requires-Dist: types-PyYAML>=6.0.0; extra == "dev"
Requires-Dist: jupyter>=1.0.0; extra == "dev"
Requires-Dist: notebook>=6.0.0; extra == "dev"
Provides-Extra: all
Requires-Dist: liana>=0.1.0; extra == "all"
Requires-Dist: cellphonedb>=3.0.0; extra == "all"
Requires-Dist: omnipath>=1.0.0; extra == "all"
Requires-Dist: fastapi>=0.100.0; extra == "all"
Requires-Dist: uvicorn>=0.23.0; extra == "all"
Requires-Dist: pydantic>=2.0.0; extra == "all"
Requires-Dist: pytest>=7.0.0; extra == "all"
Requires-Dist: pytest-cov>=4.0.0; extra == "all"
Requires-Dist: black>=23.0.0; extra == "all"
Requires-Dist: flake8>=6.0.0; extra == "all"
Requires-Dist: mypy>=1.0.0; extra == "all"
Requires-Dist: types-PyYAML>=6.0.0; extra == "all"
Requires-Dist: jupyter>=1.0.0; extra == "all"
Requires-Dist: notebook>=6.0.0; extra == "all"
Dynamic: author
Dynamic: author-email
Dynamic: classifier
Dynamic: description
Dynamic: description-content-type
Dynamic: home-page
Dynamic: keywords
Dynamic: license-file
Dynamic: project-url
Dynamic: provides-extra
Dynamic: requires-dist
Dynamic: requires-python
Dynamic: summary
